strct/__init__.py
strct/_version.py
strct/version.info
strct/dicts/__init__.py
strct/dicts/_dict.py
strct/hash/__init__.py
strct/hash/_hash.py
strct/lists/__init__.py
strct/lists/_list.py
strct/sets/__init__.py
strct/sets/_set.py
strct/sortedlists/__init__.py
strct/sortedlists/sortedlist.py
strct-0.0.35.dist-info/licenses/LICENSE
strct-0.0.35.dist-info/METADATA
strct-0.0.35.dist-info/WHEEL
strct-0.0.35.dist-info/top_level.txt
strct-0.0.35.dist-info/RECORD
